ShenqiZhidao/Dockerfile
ShenqiZhidao/README.md
ShenqiZhidao/__init__.py
ShenqiZhidao/__main__.py
ShenqiZhidao/file.epub
ShenqiZhidao/index.html
ShenqiZhidao/css/__init__.py
ShenqiZhidao/css/annotations.css
ShenqiZhidao/css/main.css
ShenqiZhidao/css/normalize.css
ShenqiZhidao/css/popup.css
ShenqiZhidao/font/__init__.py
ShenqiZhidao/font/fontello.eot
ShenqiZhidao/font/fontello.svg
ShenqiZhidao/font/fontello.ttf
ShenqiZhidao/font/fontello.woff
ShenqiZhidao/img/__init__.py
ShenqiZhidao/img/annotator-glyph-sprite.png
ShenqiZhidao/img/annotator-icon-sprite.png
ShenqiZhidao/img/apple-touch-icon.png
ShenqiZhidao/img/cancelfullscreen.png
ShenqiZhidao/img/close.png
ShenqiZhidao/img/fullscreen.png
ShenqiZhidao/img/loader.gif
ShenqiZhidao/img/menu-icon.png
ShenqiZhidao/img/save.png
ShenqiZhidao/img/saved.png
ShenqiZhidao/img/settings-s.png
ShenqiZhidao/img/settings.png
ShenqiZhidao/img/star.png
ShenqiZhidao/js/__init__.py
ShenqiZhidao/js/epub.js
ShenqiZhidao/js/epub.min.js
ShenqiZhidao/js/epub.min.map
ShenqiZhidao/js/hooks.min.js
ShenqiZhidao/js/hooks.min.map
ShenqiZhidao/js/reader.js
ShenqiZhidao/js/reader.js.map
ShenqiZhidao/js/reader.min.js
ShenqiZhidao/js/reader.min.map
ShenqiZhidao/js/hooks/__init__.py
ShenqiZhidao/js/hooks/extensions/__init__.py
ShenqiZhidao/js/hooks/extensions/highlight.js
ShenqiZhidao/js/libs/__init__.py
ShenqiZhidao/js/libs/jquery.min.js
ShenqiZhidao/js/libs/localforage.min.js
ShenqiZhidao/js/libs/screenfull.js
ShenqiZhidao/js/libs/screenfull.min.js
ShenqiZhidao/js/libs/zip.min.js
ShenqiZhidao/js/plugins/__init__.py
ShenqiZhidao/js/plugins/hypothesis.js
ShenqiZhidao/js/plugins/search.js
shenqi_zhidao-2022.10.9.1.dist-info/METADATA
shenqi_zhidao-2022.10.9.1.dist-info/WHEEL
shenqi_zhidao-2022.10.9.1.dist-info/entry_points.txt
shenqi_zhidao-2022.10.9.1.dist-info/top_level.txt
shenqi_zhidao-2022.10.9.1.dist-info/RECORD
